lonedruid/__init__.py
lonedruid-0.6.2.dist-info/LICENSE
lonedruid-0.6.2.dist-info/METADATA
lonedruid-0.6.2.dist-info/WHEEL
lonedruid-0.6.2.dist-info/RECORD
