Metadata-Version: 2.1
Name: lonedruid
Version: 0.6.2
Summary: 
Home-page: https://github.com/NikitaNightBot/LoneDruid
Author: lone_druid
Author-email: enikita332@gmail.com
Requires-Python: >=3.11,<4.0
Classifier: Programming Language :: Python :: 3
Classifier: Programming Language :: Python :: 3.11
Project-URL: Repository, https://github.com/NikitaNightBot/LoneDruid
